torchconfig/__init__.py
torchconfig/filter.py
torchconfig/nn.py
torchconfig/optim.py
torchconfig-0.1.3.dist-info/METADATA
torchconfig-0.1.3.dist-info/WHEEL
torchconfig-0.1.3.dist-info/top_level.txt
torchconfig-0.1.3.dist-info/RECORD
