Metadata-Version: 2.1
Name: torchconfig
Version: 0.1.3
Summary: TorchConfig is a Python package that simplifies configuring PyTorch.
Home-page: https://github.com/seungjaeryanlee/torchconfig
Author: Seungjae Ryan Lee
Author-email: seungjaeryanlee@github.com
License: UNKNOWN
Platform: UNKNOWN
Classifier: Programming Language :: Python :: 3
Classifier: License :: OSI Approved :: MIT License
Classifier: Operating System :: OS Independent
Requires-Python: >=3.6
